<?xml version="1.0" encoding="utf-8"?>
<odoo>

     <record id="view_document_type_form" model="ir.ui.view">
            <field name="name">account.document.type</field>
            <field name="model">account.document.type</field>
            <field name="priority" eval="8" />
            <field name="arch" type="xml">
                <form>
                    <sheet>
                        <div class="oe_title">
                            <h1>
                                <table>
                                    <tr>
                                        <td>
                                            <field name="name" required="1" placeholder="Name"/>
                                        </td>
                                    </tr>
                                </table>
                            </h1>
                        </div>
                        <group>
                            <group>
                                
                            </group>
                        </group>
                    </sheet>
                </form>
            </field>
        </record>

    <record id="view_document_type_tree" model="ir.ui.view">
        <field name="name">account.document.type.tree</field>
        <field name="model">account.document.type</field>
        <field name="arch" type="xml">
            <tree string="Document Type">
                <field name="name"/>
            </tree>
        </field>
    </record>

    <record model="ir.actions.act_window" id="action_document_type">
        <field name="name">Document Types</field>
        <field name="res_model">account.document.type</field>
        <field name="view_mode">tree,form</field>
        <field name="domain">[]</field>
        <field name="help" type="html">
            <p class="oe_view_nocontent_create">
                Create new record
            </p>
        </field>
    </record>

    <menuitem action="action_document_type" id="menu_document_type" sequence="20" parent="account.account_account_menu"/>

</odoo>
